possinote/__init__.py
possinote/client.py
possinote/email_service.py
possinote/exceptions.py
possinote/scheduling.py
possinote/sms.py
possinote-1.0.0.dist-info/METADATA
possinote-1.0.0.dist-info/WHEEL
possinote-1.0.0.dist-info/top_level.txt
possinote-1.0.0.dist-info/RECORD
